fluf/__init__.py
fluf/app.py
fluf/cli/__init__.py
fluf/cli/__init__.py~
fluf/cli/core.py
fluf/cli/core.py~
fluf/data.py
fluf/datatypes.py
fluf/db.py
fluf/etc/__init__.py
fluf/etc/fluf_config.yaml
fluf/models.py
fluf/plugin/__init__.py
fluf/plugin/calltracer.py
fluf/plugin/config.py
fluf/plugin/db.py
fluf/plugin/diskcache.py
fluf/plugin/executor.py
fluf/plugin/logger.py
fluf/plugin/memcache.py
fluf/util.py
fluf-0.2.dist-info/LICENSE
fluf-0.2.dist-info/WHEEL
fluf-0.2.dist-info/METADATA
fluf-0.2.dist-info/RECORD
